[
  {
    "id": 21,
    "image": "Metal_Mario_Spirit.png",
    "name": "Metal Mario",
    "type": "shield",
    "rarity": 3,
    "slot": 1,
    "power": 8156,
    "attack": 1539,
    "defense": 6156,
    "effect": "Weight ↑",
    "origin": "Super Mario 64",
    "obtain": "•Battle via Spirit Board<br>•Purchase from the Vault Shop for 6000G"
  },
  {
    "id": 28,
    "image": "Catpeach.png",
    "name": "Cat Princess Peach",
    "type": "shield",
    "rarity": 3,
    "slot": 3,
    "power": 9346,
    "attack": 4853,
    "defense": 4134,
    "effect": "Weight ↓",
    "origin": "Super Mario 3D World",
    "obtain": "•Summon with cores from Rover and Baby Peach"
  },
  {
    "id": 30,
    "image": "SPI-Bowser_(Wedding).png",
    "name": "Bowser",
    "type": "grab",
    "rarity": 3,
    "slot": 2,
    "power": 8516,
    "attack": 5536,
    "defense": 2980,
    "effect": "No Effect",
    "origin": "Super Mario Odyssey",
    "obtain": "•Battle via World of Light (The Final Battle - Dark)<br>•Battle via Spirit Board<br>•Purchase from the Vault Shop for 6000G<br>•Scan the Wedding Bowser amiibo"
  },
  {
    "id": 31,
    "image": "Toad_Spirit.png",
    "name": "Toad",
    "type": "grab",
    "rarity": 2,
    "slot": 3,
    "power": 5727,
    "attack": 2520,
    "defense": 3207,
    "effect": "Can Be Enhanced at Lv. 99",
    "origin": "Super Mario Bros.",
    "obtain": "•Battle via Spirit Board<br>•Purchase from the Vault Shop for 1000G<br>•Scan the Toad amiibo"
  },
  {
    "id": 32,
    "image": "Captain_Toad_Spirit.png",
    "name": "Captain Toad",
    "type": "grab",
    "rarity": 3,
    "slot": 3,
    "power": 9453,
    "attack": 4454,
    "defense": 4636,
    "effect": "Item Gravitation",
    "origin": "Super Mario Galaxy",
    "obtain": "•Enhance the Toad spirit"
  },
  {
    "id": 35,
    "image": "Waluigi_Spirit.png",
    "name": "Waluigi",
    "type": "neutral",
    "rarity": 3,
    "slot": 3,
    "power": 8579,
    "attack": 5362,
    "defense": 2887,
    "effect": "Foot Attack ↑",
    "origin": "Mario Tennis",
    "obtain": "•Battle via Spirit Board<br>•Purchase from the Vault Shop for 6000G<br>•Scan the Waluigi amiibo"
  },
  {
    "id": 36,
    "image": "Goomba_Spirit.png",
    "name": "Goomba",
    "type": "neutral",
    "rarity": 1,
    "slot": 2,
    "power": 3758,
    "attack": 1807,
    "defense": 1807,
    "effect": "Foot Attack ↑",
    "origin": "Super Mario Bros.",
    "obtain": "•Battle via World of Light (The Light Realm)<br>•Battle via Spirit Board<br>•Purchase from the Vault Shop for 500G<br>•Scan the Goomba amiibo"
  },
  {
    "id": 38,
    "image": "Hammer_Bro_Spirit.png",
    "name": "Hammer Bro",
    "type": "grab",
    "rarity": 2,
    "slot": 1,
    "power": 6212,
    "attack": 4103,
    "defense": 1758,
    "effect": "Jump ↑",
    "origin": "Super Mario Bros.",
    "obtain": "•Battle via Spirit Board<br>•Purchase from the Vault Shop for 1000G"
  },
  {
    "id": 39,
    "image": "Iggyandco.png",
    "name": "Lakitu &amp; Spiny",
    "type": "grab",
    "rarity": 2,
    "slot": 3,
    "power": 6434,
    "attack": 3279,
    "defense": 2908,
    "effect": "Weight ↓",
    "origin": "Super Mario Bros.",
    "obtain": "•Battle via World of Light (Mysterious Dimension)<br>•Battle via Spirit Board<br>•Purchase from the Vault Shop for 1000G"
  },
  {
    "id": 40,
    "image": "Blooper_spirit.png",
    "name": "Blooper",
    "type": "shield",
    "rarity": 1,
    "slot": 1,
    "power": 5974,
    "attack": 2384,
    "defense": 3361,
    "effect": "Weight ↓",
    "origin": "Super Mario Bros.",
    "obtain": "•Battle via World of Light (The Light Realm)<br>•Battle via Spirit Board<br>•Purchase from the Vault Shop for 500G"
  },
  {
    "id": 41,
    "image": "Bulletbill.png",
    "name": "Bullet Bill",
    "type": "attack",
    "rarity": 1,
    "slot": 1,
    "power": 4530,
    "attack": 2877,
    "defense": 1653,
    "effect": "Can Be Enhanced at Lv. 99",
    "origin": "Super Mario Bros.",
    "obtain": "•Battle via World of Light (The Light Realm)<br>•Battle via Spirit Board<br>•Purchase from the Vault Shop for 500G"
  },
  {
    "id": 42,
    "image": "Banzai_Bill_Spirit.png",
    "name": "Banzai Bill",
    "type": "attack",
    "rarity": 2,
    "slot": 1,
    "power": 7475,
    "attack": 4708,
    "defense": 2480,
    "effect": "Impact Run",
    "origin": "Super Mario World",
    "obtain": "•Enhance the Bullet Bill spirit"
  },
  {
    "id": 43,
    "image": "Shyguy.png",
    "name": "Shy Guy",
    "type": "neutral",
    "rarity": 1,
    "slot": 2,
    "power": 3979,
    "attack": 2085,
    "defense": 1741,
    "effect": "Fist Attack ↑",
    "origin": "Yume Kōjō: Doki Doki Panic",
    "obtain": "•Battle via World of Light (The Light Realm)<br>•Battle via Spirit Board<br>•Purchase from the Vault Shop for 500G"
  },
  {
    "id": 45,
    "image": "Birdo_Spirit.png",
    "name": "Birdo",
    "type": "grab",
    "rarity": 3,
    "slot": 2,
    "power": 8516,
    "attack": 3917,
    "defense": 4599,
    "effect": "No Effect",
    "origin": "Yume Kōjō: Doki Doki Panic",
    "obtain": "•Summon with cores from T-Rex and Starly"
  },
  {
    "id": 46,
    "image": "Mouser.png",
    "name": "Mouser",
    "type": "grab",
    "rarity": 1,
    "slot": 1,
    "power": 5548,
    "attack": 2885,
    "defense": 2663,
    "effect": "No Effect",
    "origin": "Yume Kōjō: Doki Doki Panic",
    "obtain": "•Battle via World of Light (The Light Realm)<br>•Battle via Spirit Board<br>•Purchase from the Vault Shop for 500G"
  },
  {
    "id": 47,
    "image": "Wart.png",
    "name": "Wart",
    "type": "grab",
    "rarity": 2,
    "slot": 2,
    "power": 6180,
    "attack": 2719,
    "defense": 3461,
    "effect": "No Effect",
    "origin": "Yume Kōjō: Doki Doki Panic",
    "obtain": "•Battle via World of Light (The Light Realm)<br>•Battle via Spirit Board<br>•Purchase from the Vault Shop for 1000G"
  },
  {
    "id": 48,
    "image": "Boo_Spirit.png",
    "name": "Boo",
    "type": "neutral",
    "rarity": 1,
    "slot": 3,
    "power": 4035,
    "attack": 1715,
    "defense": 2320,
    "effect": "Can Be Enhanced at Lv. 99",
    "origin": "Super Mario Bros. 3",
    "obtain": "•Battle via World of Light (Dracula's Castle)<br>•Battle via Spirit Board<br>•Purchase from the Vault Shop for 500G<br>•Scan the Boo amiibo"
  },
  {
    "id": 49,
    "image": "KB_Spirit.png",
    "name": "King Boo",
    "type": "neutral",
    "rarity": 2,
    "slot": 3,
    "power": 6612,
    "attack": 3020,
    "defense": 3338,
    "effect": "Floaty Jumps",
    "origin": "Luigi's Mansion",
    "obtain": "•Enhance the Boo spirit"
  },
  {
    "id": 51,
    "image": "Chainchomp.png",
    "name": "Chain Chomp",
    "type": "attack",
    "rarity": 2,
    "slot": 0,
    "power": 7062,
    "attack": 3898,
    "defense": 2765,
    "effect": "Weight ↑",
    "origin": "Super Mario Bros. 3",
    "obtain": "•Purchase at Timmy and Tommy's for 1000SP<br>•Battle via Spirit Board"
  },
  {
    "id": 53,
    "image": "Nipper_Plant_Spirit.png",
    "name": "Nipper Plant",
    "type": "grab",
    "rarity": 1,
    "slot": 2,
    "power": 4309,
    "attack": 2176,
    "defense": 2133,
    "effect": "Can Be Enhanced at Lv. 99",
    "origin": "Super Mario Bros. 3",
    "obtain": "•Purchase at Beedle's Tent for 500SP<br>•Battle via Spirit Board"
  },
  {
    "id": 54,
    "image": "Petey_Piranha_Spirit.png",
    "name": "Petey Piranha",
    "type": "grab",
    "rarity": 3,
    "slot": 2,
    "power": 9989,
    "attack": 4862,
    "defense": 3978,
    "effect": "Giant",
    "origin": "Super Mario Sunshine",
    "obtain": "•Enhance the Nipper Plant spirit"
  },
  {
    "id": 55,
    "image": "Boom_Boom_Spirit.png",
    "name": "Boom Boom",
    "type": "attack",
    "rarity": 2,
    "slot": 1,
    "power": 6650,
    "attack": 2660,
    "defense": 3990,
    "effect": "Can Be Enhanced at Lv. 99",
    "origin": "Super Mario Bros. 3",
    "obtain": "•Battle via World of Light (The Light Realm)<br>•Battle via Spirit Board<br>•Purchase from the Vault Shop for 1000G"
  },
  {
    "id": 56,
    "image": "Boomboompowpow.png",
    "name": "Boom Boom &amp; Pom Pom",
    "type": "attack",
    "rarity": 3,
    "slot": 1,
    "power": 9271,
    "attack": 3877,
    "defense": 4552,
    "effect": "Hyper Smash Attacks",
    "origin": "Super Mario Bros 3 and Super Mario 3D Land",
    "obtain": "•Enhance the Boom Boom spirit"
  },
  {
    "id": 57,
    "image": "Tatanga.png",
    "name": "Tatanga",
    "type": "shield",
    "rarity": 2,
    "slot": 2,
    "power": 6879,
    "attack": 3405,
    "defense": 3474,
    "effect": "No Effect",
    "origin": "Super Mario Land",
    "obtain": "•Battle via Spirit Board<br>•Purchase from the Vault Shop for 1000G"
  },
  {
    "id": 59,
    "image": "Chuck.png",
    "name": "Chargin' Chuck",
    "type": "attack",
    "rarity": 1,
    "slot": 1,
    "power": 4536,
    "attack": 1134,
    "defense": 3402,
    "effect": "No Effect",
    "origin": "Super Mario World",
    "obtain": "•Battle via World of Light (The Light Realm)<br>•Battle via Spirit Board<br>•Purchase from the Vault Shop for 500G"
  },
  {
    "id": 61,
    "image": "Kamek_Spirit.png",
    "name": "Kamek",
    "type": "grab",
    "rarity": 2,
    "slot": 1,
    "power": 6583,
    "attack": 2702,
    "defense": 3509,
    "effect": "Magic Attack ↑",
    "origin": "Super Mario World 2: Yoshi's Island",
    "obtain": "•Battle via World of Light (Molten Fortress)<br>•Battle via Spirit Board (unlocked after obtaining spirit once)<br>•Purchase from the Vault Shop for 1000G (unlocked after obtaining spirit once)"
  },
  {
    "id": 63,
    "image": "Dry_Bowser_",
    "name": "Dry Bowser",
    "type": "shield",
    "rarity": 4,
    "slot": 1,
    "power": 12137,
    "attack": 4579,
    "defense": 6455,
    "effect": "Fire Attack ↑",
    "origin": "New Super Mario Bros.",
    "obtain": "•Battle via World of Light (Dracula's Castle)<br>•Battle via Spirit Board<br>•Purchase from the Vault Shop for 15,000G"
  },
  {
    "id": 65,
    "image": "SPI-Big_Urchin.png",
    "name": "Big Urchin",
    "type": "shield",
    "rarity": 2,
    "slot": 1,
    "power": 7670,
    "attack": 3618,
    "defense": 3618,
    "effect": "Electric Weakness",
    "origin": "New Super Mario Bros. Wii",
    "obtain": "•Purchase at Beedle's Tent for 1000SP<br>•Battle via Spirit Board"
  },
  {
    "id": 66,
    "image": "Kingbomomb.png",
    "name": "King Bob-omb",
    "type": "attack",
    "rarity": 2,
    "slot": 1,
    "power": 7248,
    "attack": 3590,
    "defense": 3248,
    "effect": "Throw Power ↑",
    "origin": "Super Mario 64",
    "obtain": "•Summon with cores from Shake King and Bob-omb<br>•Battle via Spirit Board (unlocked after obtaining spirit once)<br>•Purchase from the Vault Shop for 1000G (unlocked after obtaining spirit once)"
  },
  {
    "id": 70,
    "image": "Shadow_Mario_Spirit.png",
    "name": "Shadow Mario",
    "type": "neutral",
    "rarity": 3,
    "slot": 3,
    "power": 8007,
    "attack": 4444,
    "defense": 3563,
    "effect": "No Effect",
    "origin": "Super Mario Sunshine",
    "obtain": ""
  },
  {
    "id": 81,
    "image": "Goo_Goo_Buggy_Spirit.png",
    "name": "Goo-Goo Buggy",
    "type": "attack",
    "rarity": 2,
    "slot": 2,
    "power": 6928,
    "attack": 3631,
    "defense": 3031,
    "effect": "Weight ↓",
    "origin": "Mario Kart: Double Dash!!",
    "obtain": "•Complete Challenge (Smash): <i>Get 3 KOs within the first minute of a battle,<br>•Purchase from the Vault Shop for 1000G (unlocked after obtaining spirit once)"
  },
  {
    "id": 88,
    "image": "Toad_in_cheep_charger.png",
    "name": "Cheep Charger",
    "type": "grab",
    "rarity": 1,
    "slot": 1,
    "power": 4951,
    "attack": 2190,
    "defense": 2571,
    "effect": "Speed ↑",
    "origin": "Mario Kart Wii",
    "obtain": "•Battle via Spirit Board<br>•Purchase from the Vault Shop for 500G"
  },
  {
    "id": 90,
    "image": "Biddybuggy_Spirit.png",
    "name": "Biddybuggy",
    "type": "grab",
    "rarity": 2,
    "slot": 1,
    "power": 8385,
    "attack": 3548,
    "defense": 4515,
    "effect": "Weight ↓",
    "origin": "Mario Kart 8",
    "obtain": "•Battle via Spirit Board<br>•Purchase from the Vault Shop for 1000G"
  },
  {
    "id": 91,
    "image": "Badwagon_Spirit.png",
    "name": "Badwagon",
    "type": "shield",
    "rarity": 3,
    "slot": 2,
    "power": 7904,
    "attack": 3534,
    "defense": 4066,
    "effect": "Speed ↑",
    "origin": "Mario Kart 8",
    "obtain": "•Purchase at Funky Kong's Shack for 4000SP<br>•Battle via Spirit Board"
  },
  {
    "id": 93,
    "image": "Master_Cycle_Spirit.png",
    "name": "Master Cycle",
    "type": "grab",
    "rarity": 4,
    "slot": 2,
    "power": 10440,
    "attack": 5471,
    "defense": 4568,
    "effect": "Speed ↑",
    "origin": "Mario Kart 8",
    "obtain": ""
  },
  {
    "id": 94,
    "image": "Papermario.png",
    "name": "Paper Mario",
    "type": "neutral",
    "rarity": 3,
    "slot": 3,
    "power": 9724,
    "attack": 5042,
    "defense": 3962,
    "effect": "Water Weakness",
    "origin": "Paper Mario",
    "obtain": ""
  },
  {
    "id": 95,
    "image": "Paper_Bowser_Spirit.png",
    "name": "Paper Bowser",
    "type": "attack",
    "rarity": 3,
    "slot": 2,
    "power": 9005,
    "attack": 5178,
    "defense": 3827,
    "effect": "Can Be Enhanced at Lv. 99",
    "origin": "Paper Mario",
    "obtain": "•Battle via Spirit Board<br>•Purchase from the Vault Shop for 6000G"
  },
  {
    "id": 96,
    "image": "Paper_Bowser_Sticker_Spirit.png",
    "name": "Paper Bowser (Paper Mario: Sticker Star)",
    "type": "attack",
    "rarity": 4,
    "slot": 2,
    "power": 11640,
    "attack": 5768,
    "defense": 4719,
    "effect": "Mouthful of Curry",
    "origin": "Paper Mario: Sticker Star",
    "obtain": "•Enhance the Paper Bowser spirit"
  },
  {
    "id": 97,
    "image": "Kammy_Koopa.png",
    "name": "Kammy Koopa",
    "type": "attack",
    "rarity": 1,
    "slot": 1,
    "power": 5255,
    "attack": 2231,
    "defense": 2727,
    "effect": "Magic Attack ↑",
    "origin": "Paper Mario",
    "obtain": "•Battle via World of Light (The Light Realm)<br>•Battle via Spirit Board (unlocked after obtaining spirit once)<br>•Purchase from the Vault Shop for 500G (unlocked after obtaining spirit once)"
  },
  {
    "id": 98,
    "image": "Vivian_Spirit.png",
    "name": "Vivian",
    "type": "shield",
    "rarity": 2,
    "slot": 1,
    "power": 7926,
    "attack": 3392,
    "defense": 4230,
    "effect": "Weight ↓",
    "origin": "Paper Mario: The Thousand-Year Door",
    "obtain": "•Battle via Spirit Board<br>•Purchase from the Vault Shop for 1000G"
  },
  {
    "id": 99,
    "image": "Shadowqueen.png",
    "name": "Shadow Queen",
    "type": "attack",
    "rarity": 3,
    "slot": 2,
    "power": 9359,
    "attack": 5475,
    "defense": 3884,
    "effect": "No Effect",
    "origin": "Paper Mario: The Thousand-Year Door",
    "obtain": "•Summon with cores from Vivian and Gengar"
  },
  {
    "id": 100,
    "image": "Mr_L_Spirit.png",
    "name": "Mr. L",
    "type": "attack",
    "rarity": 2,
    "slot": 2,
    "power": 7976,
    "attack": 4210,
    "defense": 3176,
    "effect": "Water Weakness",
    "origin": "Super Paper Mario",
    "obtain": "•Battle via World of Light (Sacred Land)<br>•Battle via Spirit Board<br>•Purchase from the Vault Shop for 1000G"
  },
  {
    "id": 101,
    "image": "DimentioSpirit.png",
    "name": "Dimentio",
    "type": "grab",
    "rarity": 2,
    "slot": 3,
    "power": 7449,
    "attack": 3259,
    "defense": 3904,
    "effect": "Weight ↓",
    "origin": "Super Paper Mario",
    "obtain": "•Battle via Spirit Board<br>•Purchase from the Vault Shop for 1000G"
  },
  {
    "id": 104,
    "image": "Genosmrpg.png",
    "name": "Geno",
    "type": "attack",
    "rarity": 4,
    "slot": 3,
    "power": 10000,
    "attack": 5250,
    "defense": 4750,
    "effect": "No Effect",
    "origin": "Super Mario RPG: Legend of the Seven Stars",
    "obtain": ""
  },
  {
    "id": 105,
    "image": "PrincePeasleySpirit.png",
    "name": "Prince Peasley",
    "type": "shield",
    "rarity": 1,
    "slot": 1,
    "power": 4503,
    "attack": 2409,
    "defense": 2094,
    "effect": "No Effect",
    "origin": "Mario &amp; Luigi: Superstar Saga",
    "obtain": "•Battle via World of Light (The Light Realm)<br>•Battle via Spirit Board<br>•Purchase from the Vault Shop for 500G"
  },
  {
    "id": 106,
    "image": "FawfulSpiritSSBU.png",
    "name": "Fawful",
    "type": "neutral",
    "rarity": 2,
    "slot": 3,
    "power": 6138,
    "attack": 3185,
    "defense": 2606,
    "effect": "Electric Attack ↑",
    "origin": "Mario &amp; Luigi: Superstar Saga",
    "obtain": "•Battle via Spirit Board<br>•Purchase from the Vault Shop for 1000G"
  },
  {
    "id": 107,
    "image": "Princessshroob.png",
    "name": "Princess Shroob",
    "type": "neutral",
    "rarity": 2,
    "slot": 3,
    "power": 6349,
    "attack": 3365,
    "defense": 2984,
    "effect": "No Effect",
    "origin": "Mario &amp; Luigi: Partners in Time",
    "obtain": "•Battle via Spirit Board<br>•Purchase from the Vault Shop for 1000G"
  },
  {
    "id": 109,
    "image": "Broque_Monsieur_Spirit.png",
    "name": "Broque Monsieur",
    "type": "shield",
    "rarity": 1,
    "slot": 1,
    "power": 5019,
    "attack": 1832,
    "defense": 3187,
    "effect": "No Effect",
    "origin": "Mario &amp; Luigi: Bowser's Inside Story",
    "obtain": "•Battle via Spirit Board<br>•Purchase from the Vault Shop for 500G"
  },
  {
    "id": 110,
    "image": "Dreambert.png",
    "name": "Dreambert",
    "type": "shield",
    "rarity": 1,
    "slot": 2,
    "power": 4535,
    "attack": 2131,
    "defense": 2404,
    "effect": "No Effect",
    "origin": "Mario &amp; Luigi: Dream Team",
    "obtain": "•Battle via World of Light (The Light Realm)<br>•Battle via Spirit Board<br>•Purchase from the Vault Shop for 500G"
  },
  {
    "id": 112,
    "image": "Papercraft_Mario_Spirit.png",
    "name": "Papercraft Mario",
    "type": "attack",
    "rarity": 1,
    "slot": 3,
    "power": 5187,
    "attack": 3068,
    "defense": 1920,
    "effect": "Fire Weakness",
    "origin": "Mario &amp; Luigi: Paper Jam",
    "obtain": "•Purchase at Funky Kong's Shack for 500SP"
  },
  {
    "id": 115,
    "image": "Eggplant_Man.png",
    "name": "Eggplant Man",
    "type": "shield",
    "rarity": 1,
    "slot": 1,
    "power": 4773,
    "attack": 2172,
    "defense": 2601,
    "effect": "No Effect",
    "origin": "Wrecking Crew",
    "obtain": "•Battle via Spirit Board<br>•Purchase from the Vault Shop for 500G"
  },
  {
    "id": 124,
    "image": "Waluigi",
    "name": "Waluigi",
    "type": "grab",
    "rarity": 2,
    "slot": 1,
    "power": 6479,
    "attack": 3271,
    "defense": 2959,
    "effect": "Foot Attack ↑",
    "origin": "Mario Strikers Charged",
    "obtain": "•Battle via Spirit Board<br>•Purchase from the Vault Shop for 1000G"
  },
  {
    "id": 125,
    "image": "Petepiranhastrikers.png",
    "name": "Petey Piranha",
    "type": "grab",
    "rarity": 2,
    "slot": 1,
    "power": 6696,
    "attack": 3214,
    "defense": 3482,
    "effect": "No Effect",
    "origin": "Mario Strikers Charged",
    "obtain": "•Battle via Spirit Board<br>•Purchase from the Vault Shop for 1000G"
  },
  {
    "id": 126,
    "image": "Mini_Mario_Spirit.png",
    "name": "Mini Mario",
    "type": "neutral",
    "rarity": 2,
    "slot": 3,
    "power": 6336,
    "attack": 3580,
    "defense": 2756,
    "effect": "Can Be Enhanced at Lv. 99",
    "origin": "Mario vs. Donkey Kong",
    "obtain": "•Purchase at Timmy and Tommy's for 1000SP"
  },
  {
    "id": 127,
    "image": "Mini_Mario_Hammer_Spirit.png",
    "name": "Mini Mario &amp; Hammers",
    "type": "neutral",
    "rarity": 3,
    "slot": 3,
    "power": 8917,
    "attack": 4789,
    "defense": 3468,
    "effect": "Hammer Duration ↑",
    "origin": "Mario vs. Donkey Kong 2: March of the Minis",
    "obtain": "•Enhance the Mini Mario spirit"
  },
  {
    "id": 129,
    "image": "Rabbidpeach.png",
    "name": "Rabbid 'Peach'",
    "type": "shield",
    "rarity": 2,
    "slot": 1,
    "power": 6944,
    "attack": 2882,
    "defense": 3669,
    "effect": "Jump ↑",
    "origin": "Mario + Rabbids Kingdom Battle",
    "obtain": "•Battle via Spirit Board<br>•Purchase from the Vault Shop for 1000G"
  },
  {
    "id": 130,
    "image": "Rabbid_Mario.png",
    "name": "Rabbid 'Mario'",
    "type": "attack",
    "rarity": 2,
    "slot": 1,
    "power": 6590,
    "attack": 2487,
    "defense": 3730,
    "effect": "Jump ↑",
    "origin": "Mario + Rabbids Kingdom Battle",
    "obtain": "•Battle via World of Light (The Light Realm)<br>•Battle via Spirit Board<br>•Purchase from the Vault Shop for 1000G"
  },
  {
    "id": 131,
    "image": "Rabbitsdonkey.png",
    "name": "Rabbid Kong",
    "type": "attack",
    "rarity": 1,
    "slot": 1,
    "power": 4534,
    "attack": 3209,
    "defense": 1069,
    "effect": "Weight ↑",
    "origin": "Mario + Rabbids Kingdom Battle",
    "obtain": "•Battle via World of Light (The Light Realm)<br>•Battle via Spirit Board<br>•Purchase from the Vault Shop for 500G"
  }
]